[{"type": "dataset", "prodId": "c88d0058-3af3-4034-9915-1c8b336cfb62", "stagingId": "466e622c-80b7-4ed1-b2b6-581b5d3cb7d4"}, {"type": "layer", "prodId": "a71f7b03-9de1-40c1-b853-c134bce1fd83", "stagingId": "be1056ff-e8f4-46bc-b45f-4c7357ecb213"}, {"type": "widget", "prodId": "72874f62-9b18-4f1f-b14a-97554978fab7", "stagingId": "d810c6b6-522f-493c-8966-fa983f8bf170"}, {"type": "metadata", "prodId": "60e8bf9002e477001a6bec1e", "stagingId": [{"id": "60ec79da7af3b7001b7101d5", "type": "metadata", "attributes": {"dataset": "466e622c-80b7-4ed1-b2b6-581b5d3cb7d4", "application": "rw", "resource": {"id": "d810c6b6-522f-493c-8966-fa983f8bf170", "type": "widget"}, "language": "en", "info": {"caption": ""}, "createdAt": "2021-07-12T17:20:26.613Z", "updatedAt": "2021-07-12T17:20:26.613Z", "status": "published"}}]}, {"type": "metadata", "prodId": "60ec465602e477001a6bec1f", "stagingId": [{"id": "60ec79dc7af3b7001b7101d6", "type": "metadata", "attributes": {"dataset": "466e622c-80b7-4ed1-b2b6-581b5d3cb7d4", "application": "rw", "resource": {"id": "466e622c-80b7-4ed1-b2b6-581b5d3cb7d4", "type": "dataset"}, "language": "en", "name": "", "description": "hold", "source": "", "info": {"name": "hold", "technical_title": "hold"}, "createdAt": "2021-07-12T17:20:28.005Z", "updatedAt": "2021-07-12T17:20:28.005Z", "status": "published"}}]}]